{
	"animations": [
		{
			"offsets": [
				0,
				0
			],
			"loop": false,
			"fps": 24,
			"anim": "idle",
			"indices": [],
			"name": "brunoli idle"
		},
		{
			"offsets": [
				0,
				0
			],
			"loop": false,
			"fps": 24,
			"anim": "singLEFT",
			"indices": [],
			"name": "brunoli left"
		},
		{
			"offsets": [
				0,
				0
			],
			"loop": false,
			"fps": 24,
			"anim": "singDOWN",
			"indices": [],
			"name": "brunoli down"
		},
		{
			"offsets": [
				0,
				0
			],
			"loop": false,
			"fps": 24,
			"anim": "singUP",
			"indices": [],
			"name": "brunoli up"
		},
		{
			"offsets": [
				0,
				0
			],
			"loop": false,
			"fps": 24,
			"anim": "singRIGHT",
			"indices": [],
			"name": "brunoli right"
		}
	],
	"no_antialiasing": false,
	"image": "characters/brunoli",
	"position": [
		-334.5,
		20
	],
	"healthicon": "gomesbruno",
	"flip_x": true,
	"healthbar_colors": [
		255,
		255,
		255
	],
	"camera_position": [
		0,
		0
	],
	"sing_duration": 6.1,
	"scale": 0.6
}